odoo10_addon_base_comment_template-10.0.1.0.0-py2.7-nspkg.pth
odoo/addons/base_comment_template/README.rst
odoo/addons/base_comment_template/__init__.py
odoo/addons/base_comment_template/__manifest__.py
odoo/addons/base_comment_template/i18n/am.po
odoo/addons/base_comment_template/i18n/ar.po
odoo/addons/base_comment_template/i18n/base_comment_template.pot
odoo/addons/base_comment_template/i18n/bg.po
odoo/addons/base_comment_template/i18n/bs.po
odoo/addons/base_comment_template/i18n/ca.po
odoo/addons/base_comment_template/i18n/cs.po
odoo/addons/base_comment_template/i18n/da.po
odoo/addons/base_comment_template/i18n/de.po
odoo/addons/base_comment_template/i18n/el_GR.po
odoo/addons/base_comment_template/i18n/en_GB.po
odoo/addons/base_comment_template/i18n/es.po
odoo/addons/base_comment_template/i18n/es_AR.po
odoo/addons/base_comment_template/i18n/es_CL.po
odoo/addons/base_comment_template/i18n/es_CO.po
odoo/addons/base_comment_template/i18n/es_CR.po
odoo/addons/base_comment_template/i18n/es_DO.po
odoo/addons/base_comment_template/i18n/es_EC.po
odoo/addons/base_comment_template/i18n/es_ES.po
odoo/addons/base_comment_template/i18n/es_MX.po
odoo/addons/base_comment_template/i18n/es_PE.po
odoo/addons/base_comment_template/i18n/es_PY.po
odoo/addons/base_comment_template/i18n/es_VE.po
odoo/addons/base_comment_template/i18n/et.po
odoo/addons/base_comment_template/i18n/eu.po
odoo/addons/base_comment_template/i18n/fa.po
odoo/addons/base_comment_template/i18n/fi.po
odoo/addons/base_comment_template/i18n/fr.po
odoo/addons/base_comment_template/i18n/fr_CA.po
odoo/addons/base_comment_template/i18n/fr_CH.po
odoo/addons/base_comment_template/i18n/gl.po
odoo/addons/base_comment_template/i18n/gl_ES.po
odoo/addons/base_comment_template/i18n/he.po
odoo/addons/base_comment_template/i18n/hr.po
odoo/addons/base_comment_template/i18n/hr_HR.po
odoo/addons/base_comment_template/i18n/hu.po
odoo/addons/base_comment_template/i18n/id.po
odoo10_addon_base_comment_template-10.0.1.0.0.dist-info/DESCRIPTION.rst
odoo10_addon_base_comment_template-10.0.1.0.0.dist-info/METADATA
odoo10_addon_base_comment_template-10.0.1.0.0.dist-info/RECORD
odoo10_addon_base_comment_template-10.0.1.0.0.dist-info/WHEEL
odoo10_addon_base_comment_template-10.0.1.0.0.dist-info/metadata.json
odoo10_addon_base_comment_template-10.0.1.0.0.dist-info/namespace_packages.txt
odoo10_addon_base_comment_template-10.0.1.0.0.dist-info/top_level.txt
